{
    "count": 20,
    "start": 0,
    "total": 3,
    "books": [
              {
              "publisher": "北京十月文艺出版社",
              "subtitle": "张爱玲全集03——小说",
              "isbn10": "7530211188",
              "isbn13": "9787530211182",
              "title": "怨女",
              "url": "http://api.douban.com/v2/book/10757942",
              "origin_title": "",
              "image": "http://img3.douban.com/mpic/s10199576.jpg",
              "alt_title": "",
              "binding": "平装",
              "author_intro": "张爱玲，1920年9月30日出生於上海，原名张煐。1922年迁居天津。1928年由天津搬回上海，读《红楼梦》和《三国演义》。1930年改名张爱玲，1939年考进香港大学，1941年太平洋战争爆发，投入文学创作。两年後，发表《倾城之恋》和《金锁记》等作品，并结识周瘦鹃、柯灵、苏青和胡兰成。1944与胡兰成结婚，1945年自编《倾城之恋》在上海公演；同年，抗战胜利。1947年与胡兰成离婚，1952年移居香港，1955年离港赴美，并拜访胡适。1956年结识剧作家赖雅，同年八月，在纽约与赖雅结婚。1967年赖雅去世，1973年定居洛杉矶；两年后，完成英译清代长篇小说《海上花列传》。1995年九月逝於洛杉矶公寓，享年七十四岁。",
              "summary": "她生于贫穷之家，因世俗虚荣的压力，嫁给一个半残废的富家少爷，虽有锦衣玉食，精神上确实茫然无依。\n有目的的爱都不是真爱，女主角的愤懑与刻薄，被张爱玲描写的几近变态，却又凄凉无比。——根据《金锁记》改写的长篇小说，被誉为文坛最美的收获之一。\n张爱玲也许不是时下“正确”定义里的女性主义者，但在《怨女》中，她从未停止对女性命运的严肃思考。——王德威",
              "price": "29.60元",
              "pages": "345",
              "author": [
                         "张爱玲"
                         ],
              "translator": [],
              "images": {
              "small": "http://img3.douban.com/spic/s10199576.jpg",
              "large": "http://img3.douban.com/lpic/s10199576.jpg",
              "medium": "http://img3.douban.com/mpic/s10199576.jpg"
              },
              "alt": "http://book.loc-zeta.douban.com/subject/10757942/",
              "pubdate": "2012-6",
              "id": "10757942",
              "tags": [
                       {
                       "count": 394,
                       "name": "张爱玲"
                       },
                       {
                       "count": 120,
                       "name": "怨女"
                       },
                       {
                       "count": 103,
                       "name": "小说"
                       },
                       {
                       "count": 43,
                       "name": "爱情"
                       },
                       {
                       "count": 40,
                       "name": "现当代文学"
                       },
                       {
                       "count": 33,
                       "name": "文学"
                       },
                       {
                       "count": 32,
                       "name": "怨女的名字很贴切"
                       },
                       {
                       "count": 32,
                       "name": "现代文学"
                       }
                       ]
              },
              {
              "publisher": "北京联合出版公司",
              "subtitle": "增订本",
              "isbn10": "7550209782",
              "isbn13": "9787550209787",
              "title": "最好的女子",
              "url": "http://api.douban.com/v2/book/20261734",
              "origin_title": "",
              "image": "http://img1.douban.com/mpic/s24227712.jpg",
              "alt_title": "",
              "binding": "平装",
              "author_intro": "黄佟佟\n当下专栏界写女子写得最好的女子，出版有散文随笔集《感情这东西》、《浮世爱情》、《最爱的男子》、《傲慢即偏见》，及长篇小说《女人是比男人更高级的动物》等，现居广州。\n长期为《南方都市报》、《南方人物周刊》、《ELLE》、《VOGUE》、《GQ》等二十多家一线媒体、品牌杂志撰写采访与专栏，被誉为“最懂女人心的专栏作家”、其专栏亦获有“传世专栏”之誉。",
              "summary": "《最好的女子》是黄佟佟迄今最畅销的传记散文集，书中所写女子皆是伴随70、80后成长的港台女明星、女作家、女艺术家，她们是这世上最美丽、最温婉、最聪慧的一群女子，看她们的人生起伏与悲欢离合、幸福哀伤与爱恨忧愁……就是看这时代女子的天性，也可得见这时代女子的天命。\n本部《最好的女子》在2010版基础上增补6万余字，尤其是新增的“佟式小词典”，信息量大，别有韵味，是目前最让作者满意，也是最具阅读与收藏价值的一版。",
              "price": "32.80元",
              "pages": "320",
              "author": [
                         "黄佟佟"
                         ],
              "translator": [],
              "images": {
              "small": "http://img1.douban.com/spic/s24227712.jpg",
              "large": "http://img1.douban.com/lpic/s24227712.jpg",
              "medium": "http://img1.douban.com/mpic/s24227712.jpg"
              },
              "alt": "http://book.loc-zeta.douban.com/subject/20261734/",
              "pubdate": "2012-11-15",
              "id": "20261734",
              "tags": [
                       {
                       "count": 376,
                       "name": "最好的女子"
                       },
                       {
                       "count": 168,
                       "name": "女性"
                       },
                       {
                       "count": 142,
                       "name": "黄佟佟"
                       },
                       {
                       "count": 129,
                       "name": "散文"
                       },
                       {
                       "count": 100,
                       "name": "女子"
                       },
                       {
                       "count": 85,
                       "name": "散文传记"
                       },
                       {
                       "count": 71,
                       "name": "生活"
                       },
                       {
                       "count": 69,
                       "name": "女人必修课"
                       }
                       ]
              },
              {
              "publisher": "",
              "subtitle": "心慢下来，行动才能快起来",
              "isbn10": "7504479306",
              "isbn13": "9787504479303",
              "title": "慢慢来，一切都来得及",
              "url": "http://api.douban.com/v2/book/20389195",
              "origin_title": "",
              "image": "http://img3.douban.com/mpic/s24444729.jpg",
              "alt_title": "",
              "binding": "",
              "author_intro": "meiya\nhttp://www.douban.com/people/meiyang/\n是豆瓣网上的一位大红人。她在上海的一家广告公司工作。\n80后双子座女生，热爱写作、阅读、跑步、旅行和美食。\n她独自在城市里孤独奋斗的同时，不忘享受生命。她把美好的生命体验记录下来，也把自己时常会有的压力、焦躁、急迫感和不安全感写下来，引起广大网友的强烈共鸣。\n她会在早上边跑步边大声哭泣来缓解压力，也会对着镜子说“我爱你呀”来鼓励自己对抗拖延症，她通过写作和阅读来学习认识生活，她活得真实，努力，因此被誉为豆瓣网最温暖、最励志的女子。\n网友们喜欢跟她倾诉心事，并从她的文字里获得正能量。\n另外，她的文章被多家杂志收入专栏，并有广播美文在“静雅思听”播出。近期出版另一本小书《这辈子最渴望做的那些事》。",
              "summary": "每个在城市中学习工作的人，都会被这本书深深的打动。\n在奋斗的道路上，我们都想快起来，快一点成功，快一点过上自己想要的生活。\n可是人就是这样的，越是着急，事情越是做不好。工作会拖延，情绪变糟糕，压力让人焦躁。\n本书的作者meiya跟我们大家一样，“独自在城市中努力的奋斗着”。她把自己这些情况都写下来，涉及到“开始爱好者”，空有梦想，不付诸行动、拖延症、注意力涣散症、负面情绪、缺乏运动，身体亚健康等等，分享有效、有趣的解决方法。她和大家一起，练习“把心慢下来，让行动快起来”。\n她还通过自己丰富的生命体验告诉大家：成功并不是最重要的，更重要的事情，是一个人心智的成熟和精神的自由。\n这也是一本促人行动的书，“允许自己慢慢来，才能重新上路”。认真的过好每天，认真的对待生命。试读的读者说，看完书，就想明早去跑步，锻炼身体。或者耐心把一些基本的事做好，开始慢慢来；学习接纳生活中的痛苦，并记录下每一份微幸福。",
              "price": "29.80元",
              "pages": "256",
              "author": [
                         "meiya"
                         ],
              "translator": [],
              "images": {
              "small": "http://img3.douban.com/spic/s24444729.jpg",
              "large": "http://img3.douban.com/lpic/s24444729.jpg",
              "medium": "http://img3.douban.com/mpic/s24444729.jpg"
              },
              "alt": "http://book.loc-zeta.douban.com/subject/20389195/",
              "pubdate": "2012-12",
              "id": "20389195",
              "tags": [
                       {
                       "count": 1926,
                       "name": "正能量"
                       },
                       {
                       "count": 1102,
                       "name": "meiya"
                       },
                       {
                       "count": 818,
                       "name": "心灵成长"
                       },
                       {
                       "count": 604,
                       "name": "励志"
                       },
                       {
                       "count": 590,
                       "name": "成长"
                       },
                       {
                       "count": 344,
                       "name": "生活"
                       },
                       {
                       "count": 300,
                       "name": "心灵"
                       },
                       {
                       "count": 189,
                       "name": "豆瓣"
                       }
                       ]
              }
              ]
}